chws_tool/__init__.py
chws_tool/add_chws.py
chws_tool/config.py
chws_tool-1.4.5.dist-info/METADATA
chws_tool-1.4.5.dist-info/WHEEL
chws_tool-1.4.5.dist-info/entry_points.txt
chws_tool-1.4.5.dist-info/licenses/LICENSE
chws_tool-1.4.5.dist-info/RECORD
