Metadata-Version: 2.4
Name: chws_tool
Version: 1.4.5
Summary: Utility for OpenType chws/vchw features
Project-URL: repository, https://github.com/googlefonts/chws_tool
Author-email: Koji Ishii <kojii@chromium.org>
License-Expression: Apache-2.0
License-File: LICENSE
Requires-Python: >=3.10
Requires-Dist: east-asian-spacing>=1.4.5
